flipper/__init__.py
flipper/client.py
flipper/decorators.py
flipper/exceptions.py
flipper/flag.py
flipper/bucketing/__init__.py
flipper/bucketing/base.py
flipper/bucketing/consistent_hash_percentage_bucketer.py
flipper/bucketing/factory.py
flipper/bucketing/noop_bucketer.py
flipper/bucketing/percentage_bucketer.py
flipper/bucketing/percentage/__init__.py
flipper/bucketing/percentage/base.py
flipper/bucketing/percentage/factory.py
flipper/bucketing/percentage/linear_ramp_percentage.py
flipper/bucketing/percentage/percentage.py
flipper/conditions/__init__.py
flipper/conditions/check.py
flipper/conditions/condition.py
flipper/conditions/operators/__init__.py
flipper/conditions/operators/equality_operator.py
flipper/conditions/operators/greater_than_operator.py
flipper/conditions/operators/greater_than_or_equal_to_operator.py
flipper/conditions/operators/interface.py
flipper/conditions/operators/less_than_operator.py
flipper/conditions/operators/less_than_or_equal_to_operator.py
flipper/conditions/operators/negated_set_membership_operator.py
flipper/conditions/operators/negation_operator.py
flipper/conditions/operators/operator.py
flipper/conditions/operators/set_membership_operator.py
flipper/contrib/__init__.py
flipper/contrib/cached.py
flipper/contrib/consul.py
flipper/contrib/interface.py
flipper/contrib/memory.py
flipper/contrib/postgresql.py
flipper/contrib/redis.py
flipper/contrib/replicated.py
flipper/contrib/s3.py
flipper/contrib/thrift.py
flipper/contrib/storage/__init__.py
flipper/contrib/storage/item.py
flipper/contrib/storage/meta.py
flipper/contrib/util/__init__.py
flipper/contrib/util/date.py
flipper/contrib/util/iter.py
flipper/events/__init__.py
flipper/events/emitter.py
flipper/events/subscriber.py
flipper/events/types.py
flipper_thrift/__init__.py
flipper_thrift/python/__init__.py
flipper_thrift/python/feature_flag_store/FeatureFlagStore.py
flipper_thrift/python/feature_flag_store/__init__.py
flipper_thrift/python/feature_flag_store/constants.py
flipper_client-1.3.2.dist-info/LICENSE.txt
flipper_client-1.3.2.dist-info/METADATA
flipper_client-1.3.2.dist-info/WHEEL
flipper_client-1.3.2.dist-info/top_level.txt
flipper_client-1.3.2.dist-info/RECORD
