Metadata-Version: 2.1
Name: flipper-client
Version: 1.3.2
Summary: UNKNOWN
Home-page: UNKNOWN
License: Apache License 2.0
Platform: UNKNOWN
Classifier: License :: OSI Approved :: Apache Software License
Requires-Dist: cachetools (<6,>=4.2.1)
Requires-Dist: python-consul (~=1.0)
Requires-Dist: redis (<5,>=2.10.6)
Requires-Dist: thrift (~=0.13)
Requires-Dist: boto3 (~=1.9)
Requires-Dist: pyee (~=6.0)
Provides-Extra: dev
Requires-Dist: six (>=1.12) ; extra == 'dev'
Requires-Dist: fakeredis (~=1.0) ; extra == 'dev'
Requires-Dist: pytest (~=7.1.0) ; extra == 'dev'
Requires-Dist: ipython ; extra == 'dev'
Requires-Dist: thrift ; extra == 'dev'
Requires-Dist: setuptools ; extra == 'dev'
Requires-Dist: wheel ; extra == 'dev'
Requires-Dist: ipdb ; extra == 'dev'
Requires-Dist: black (==22.1.0) ; extra == 'dev'
Requires-Dist: pre-commit ; extra == 'dev'
Requires-Dist: isort ; extra == 'dev'
Requires-Dist: flake8 ; extra == 'dev'
Requires-Dist: mypy ; extra == 'dev'
Requires-Dist: moto ; extra == 'dev'
Requires-Dist: bandit ; extra == 'dev'
Requires-Dist: twine ; extra == 'dev'
Requires-Dist: testing.postgresql ; extra == 'dev'
Provides-Extra: postgres
Requires-Dist: psycopg (~=3.0.10) ; extra == 'postgres'
